cse3150_jimmy_padilla_calculator/__init__.py
cse3150_jimmy_padilla_calculator/__main__.py
cse3150_jimmy_padilla_calculator/calculator.py
cse3150_jimmy_padilla_calculator/py.typed
cse3150_jimmy_padilla_calculator/file_calculator/__init__.py
cse3150_jimmy_padilla_calculator/file_calculator/file_calculator.py
cse3150_jimmy_padilla_calculator/file_calculator/nums.csv
cse3150_jimmy_padilla_calculator/tests/__init__.py
cse3150_jimmy_padilla_calculator/tests/test_file_calculator.py
cse3150_jimmy_padilla_calculator-0.4.0.dist-info/licenses/LICENSE.txt
cse3150_jimmy_padilla_calculator-0.4.0.dist-info/METADATA
cse3150_jimmy_padilla_calculator-0.4.0.dist-info/WHEEL
cse3150_jimmy_padilla_calculator-0.4.0.dist-info/entry_points.txt
cse3150_jimmy_padilla_calculator-0.4.0.dist-info/top_level.txt
cse3150_jimmy_padilla_calculator-0.4.0.dist-info/RECORD
