Metadata-Version: 2.4
Name: cse3150_jimmy_padilla_calculator
Version: 0.4.0
License-File: LICENSE.txt
Requires-Dist: tqdm~=4.0
Provides-Extra: test
Requires-Dist: types-tqdm; extra == "test"
Requires-Dist: pytest; extra == "test"
Requires-Dist: mypy; extra == "test"
Requires-Dist: ruff; extra == "test"
Requires-Dist: pre-commit; extra == "test"
Requires-Dist: tox; extra == "test"
Dynamic: license-file
